{
    "fileName": "bmf02.pdf",
    "date": "22.08.2018",
    "content": [
        {
            "type": "Fachbereich",
            "name": "Fachbereich 1",
            "persons": [
                {
                    "name": "Hr. Noack",
                    "positionType": "Hr.",
                    "contact": "-1702"
                }
            ],
            "responsibilities": [
                {
                    "respons01": "task1",
                    "respons02": "task2"
                }
            ],
            "bbox": [600, 0, 800, 200]
        }
    ]
}